hydra_plugins/lerna/__init__.py
hydra_plugins/lerna/searchpath.py
lerna/__init__.py
lerna/tests/test_all.py
lerna/tests/test_discover.py
lerna/tests/fake_package/pyproject.toml
lerna/tests/fake_package/fake_package/__init__.py
lerna/tests/fake_package/fake_package/plugin.py
lerna/tests/fake_package/fake_package/hydra/.gitkeep
lerna/tests/fake_package2/pyproject.toml
lerna/tests/fake_package2/fake_package2/__init__.py
lerna/tests/fake_package2/fake_package2/hydra/.gitkeep
lerna-1.1.0.dist-info/METADATA
lerna-1.1.0.dist-info/WHEEL
lerna-1.1.0.dist-info/licenses/LICENSE
lerna-1.1.0.dist-info/RECORD
